peakprivacy/__init__.py
peakprivacy/peakprivacy.py
peakprivacy/exceptions/__init__.py
peakprivacy/exceptions/api_connection_error.py
peakprivacy/exceptions/api_error.py
peakprivacy/exceptions/api_status_error.py
peakprivacy/exceptions/api_token_not_found_error.py
peakprivacy/exceptions/authentication_error.py
peakprivacy/exceptions/bad_request_error.py
peakprivacy/exceptions/internal_server_error.py
peakprivacy/exceptions/not_found_error.py
peakprivacy/exceptions/permission_denied_error.py
peakprivacy/exceptions/rate_limit_error.py
peakprivacy/exceptions/unprocessable_entity_error.py
peakprivacy/resources/__init__.py
peakprivacy/resources/chat.py
peakprivacy/resources/completions.py
peakprivacy/resources/models.py
peakprivacy/types/__init__.py
peakprivacy/types/api_token_valid.py
peakprivacy/types/chat_completion.py
peakprivacy/types/chat_completion_chunk.py
peakprivacy/types/chat_completion_message.py
peakprivacy/types/choice.py
peakprivacy/types/choice_delta.py
peakprivacy/types/completion_usage.py
peakprivacy/types/model.py
peakprivacy/types/model_list.py
peakprivacy/types/stream.py
peakprivacy/types/stream_choice.py
peakprivacy/utils/__init__.py
peakprivacy/utils/http_client.py
peakprivacy/validators/__init__.py
peakprivacy/validators/api_token_validator.py
peakprivacy-0.1.0.dist-info/LICENSE
peakprivacy-0.1.0.dist-info/METADATA
peakprivacy-0.1.0.dist-info/WHEEL
peakprivacy-0.1.0.dist-info/top_level.txt
peakprivacy-0.1.0.dist-info/RECORD
