Metadata-Version: 2.1
Name: peakprivacy
Version: 0.1.0
Summary: The official PeakPrivacy Python Client
Home-page: https://github.com/freihandlabor/peakprivacy-python
Author: freihandlabor GmbH
Author-email: freihandlabor GmbH <support@freihandlabor.com>
License: MIT License
Project-URL: Homepage, https://peakprivacy.ch/
Project-URL: Repository, https://github.com/freihandlabor/peakprivacy-python
Project-URL: Documentation, https://peakprivacy.ch/en/guide/api
Project-URL: Issues, https://github.com/freihandlabor/peakprivacy-python/issues
Project-URL: Changelog, https://github.com/freihandlabor/peakprivacy-python/blob/main/CHANGELOG.md
Classifier: Development Status :: 4 - Beta
Classifier: Intended Audience :: Developers
Classifier: Topic :: Software Development :: Libraries :: Python Modules
Classifier: License :: OSI Approved :: MIT License
Classifier: Programming Language :: Python :: 3.7
Classifier: Programming Language :: Python :: 3.7
Classifier: Programming Language :: Python :: 3.8
Classifier: Programming Language :: Python :: 3.9
Classifier: Programming Language :: Python :: 3.10
Classifier: Programming Language :: Python :: 3.11
Classifier: Programming Language :: Python :: 3.12
Requires-Python: >=3.7.1
License-File: LICENSE
Requires-Dist: requests >=2.31.0
Requires-Dist: typing >=3.7.4
Requires-Dist: httpx >=0.23.0
